Workbook

Sheet Painel
B2: PLANILHA DE CONTROLE DE GASTOS PESSOAIS
B3: Vero — Escola de Empresários · controle pessoal do corretor
B5: SEU MÊS
B6: Renda do mês (comissões) — preencha | C6: =12000 -> 12000
B7: Gasto total do mês | C7: =SUM(Lançamentos!$D:$D) -> 9940
B8: Custo de vida mínimo (soma dos fixos) | C8: =SUMIF(Lançamentos!$E:$E,"fixo",Lançamentos!$D:$D) -> 4800
B9: Sobra ou falta no mês | C9: =C6-C7 -> 2060
B10: % da renda comprometida | C10: =IFERROR(C7/C6,0) -> 0.82833333
B11: Pró-labore sugerido (pague-se ao menos isto) | C11: =C8 -> 4800
B13: RESERVA
B14: Reserva atual — preencha | C14: =5000 -> 5000
B15: Meta: 3x o custo de vida mínimo | C15: =C8*3 -> 14400
B16: Quanto falta para a meta | C16: =MAX(0,C15-C14) -> 9400
B18: ONDE O DINHEIRO VAI
B19: Categoria | C19: Gasto | D19: % do total
B20: Moradia | C20: =SUMIF(Lançamentos!$B:$B,B20,Lançamentos!$D:$D) -> 2640 | D20: =IFERROR(C20/$C$29,0) -> 0.26559356
B21: Alimentação | C21: =SUMIF(Lançamentos!$B:$B,B21,Lançamentos!$D:$D) -> 1800 | D21: =IFERROR(C21/$C$29,0) -> 0.18108652
B22: Transporte | C22: =SUMIF(Lançamentos!$B:$B,B22,Lançamentos!$D:$D) -> 1350 | D22: =IFERROR(C22/$C$29,0) -> 0.13581489
B23: Saúde | C23: =SUMIF(Lançamentos!$B:$B,B23,Lançamentos!$D:$D) -> 670 | D23: =IFERROR(C23/$C$29,0) -> 0.067404427
B24: Educação | C24: =SUMIF(Lançamentos!$B:$B,B24,Lançamentos!$D:$D) -> 1050 | D24: =IFERROR(C24/$C$29,0) -> 0.1056338
B25: Lazer | C25: =SUMIF(Lançamentos!$B:$B,B25,Lançamentos!$D:$D) -> 380 | D25: =IFERROR(C25/$C$29,0) -> 0.038229376
B26: Dívidas/Cartão | C26: =SUMIF(Lançamentos!$B:$B,B26,Lançamentos!$D:$D) -> 1500 | D26: =IFERROR(C26/$C$29,0) -> 0.15090543
B27: Pessoais | C27: =SUMIF(Lançamentos!$B:$B,B27,Lançamentos!$D:$D) -> 350 | D27: =IFERROR(C27/$C$29,0) -> 0.035211268
B28: Outros | C28: =SUMIF(Lançamentos!$B:$B,B28,Lançamentos!$D:$D) -> 200 | D28: =IFERROR(C28/$C$29,0) -> 0.020120724
B29: Total | C29: =SUM(C20:C28) -> 9940 | D29: =IFERROR(C29/C29,0) -> 1
B31: A conta da empresa não é a sua conta. Comece preenchendo as duas células em amarelo.

Sheet Categorias
A1: Categoria | B1: Exemplos do que entra aqui
A2: Moradia | B2: Aluguel ou financiamento, condomínio, luz, água, internet, IPTU
A3: Alimentação | B3: Mercado, feira, restaurante, delivery
A4: Transporte | B4: Combustível, manutenção e seguro do carro, pedágio, estacionamento. ATENÇÃO: se o carro roda pro trabalho, separe o pessoal do que é da empresa (zona-cinza PF x PJ).
A5: Saúde | B5: Plano de saúde, farmácia, consultas, exames
A6: Educação | B6: Escola dos filhos, cursos, livros
A7: Lazer | B7: Streaming, assinaturas, viagens, passeios
A8: Dívidas/Cartão | B8: Fatura do cartão, parcelas, empréstimos
A9: Pessoais | B9: Vestuário, cuidados pessoais, presentes
A10: Outros | B10: O que não se encaixa acima
A12: Tipo: marque cada lançamento como 'fixo' (todo mês, igual) ou 'variável' (muda de mês a mês). O custo de vida mínimo soma os fixos.

Sheet Lançamentos
A1: Data | B1: Categoria | C1: Descrição | D1: Valor | E1: Tipo
A2: 05/06/2026 | B2: Moradia | C2: Aluguel / financiamento | D2: 1800 | E2: fixo
A3: 05/06/2026 | B3: Moradia | C3: Condomínio | D3: 450 | E3: fixo
A4: 10/06/2026 | B4: Moradia | C4: Luz | D4: 180 | E4: variável
A5: 10/06/2026 | B5: Moradia | C5: Água | D5: 90 | E5: variável
A6: 08/06/2026 | B6: Moradia | C6: Internet / telefone | D6: 120 | E6: fixo
A7: 12/06/2026 | B7: Alimentação | C7: Mercado | D7: 1200 | E7: variável
A8: 15/06/2026 | B8: Alimentação | C8: Restaurante / delivery | D8: 600 | E8: variável
A9: 06/06/2026 | B9: Transporte | C9: Combustível | D9: 800 | E9: variável
A10: 06/06/2026 | B10: Transporte | C10: Manutenção / seguro do carro | D10: 400 | E10: fixo
A11: 18/06/2026 | B11: Transporte | C11: Pedágio / estacionamento | D11: 150 | E11: variável
A12: 05/06/2026 | B12: Saúde | C12: Plano de saúde | D12: 550 | E12: fixo
A13: 14/06/2026 | B13: Saúde | C13: Farmácia | D13: 120 | E13: variável
... A22: 22/06/2026 | B22: Outros | C22: Diversos | D22: 200 | E22: variável
